{
    "color": {
        "dark": {
            "magenta": {
                "100": {
                    "value": "#ff85ce",
                    "type": "color"
                },
                "200": {
                    "value": "#ff52b9",
                    "type": "color"
                },
                "300": {
                    "value": "#ff1fa5",
                    "type": "color"
                },
                "400": {
                    "value": "#eb008c",
                    "type": "color"
                },
                "500": {
                    "value": "#b8006e",
                    "type": "color"
                },
                "600": {
                    "value": "#940059",
                    "type": "color"
                },
                "700": {
                    "value": "#710043",
                    "type": "color"
                },
                "800": {
                    "value": "#4d002e",
                    "type": "color"
                },
                "900": {
                    "value": "#290019",
                    "type": "color"
                }
            },
            "editorial-green": {
                "100": {
                    "value": "#e0e1df",
                    "type": "color"
                },
                "200": {
                    "value": "#c6c8c5",
                    "type": "color"
                },
                "300": {
                    "value": "#acafab",
                    "type": "color"
                },
                "400": {
                    "value": "#939691",
                    "type": "color"
                },
                "500": {
                    "value": "#797c78",
                    "type": "color"
                },
                "600": {
                    "value": "#60625f",
                    "type": "color"
                },
                "700": {
                    "value": "#474846",
                    "type": "color"
                },
                "800": {
                    "value": "#2d2e2d",
                    "type": "color"
                },
                "900": {
                    "value": "#141414",
                    "type": "color"
                }
            },
            "etat-yellow": {
                "100": {
                    "value": "#E7E3DA",
                    "type": "color"
                },
                "200": {
                    "value": "#D3CBBB",
                    "type": "color"
                },
                "300": {
                    "value": "#BFB39C",
                    "type": "color"
                },
                "400": {
                    "value": "#AA9B7E",
                    "type": "color"
                },
                "500": {
                    "value": "#948361",
                    "type": "color"
                },
                "600": {
                    "value": "#7C6D51",
                    "type": "color"
                },
                "700": {
                    "value": "#635741",
                    "type": "color"
                },
                "800": {
                    "value": "#4A4230",
                    "type": "color"
                },
                "900": {
                    "value": "#312C20",
                    "type": "color"
                }
            },
            "inland-blue": {
                "100": {
                    "value": "#EDF1F3",
                    "type": "color"
                },
                "200": {
                    "value": "#D7E1E5",
                    "type": "color"
                },
                "300": {
                    "value": "#C2D0D7",
                    "type": "color"
                },
                "400": {
                    "value": "#ACC0C9",
                    "type": "color"
                },
                "500": {
                    "value": "#96B0BB",
                    "type": "color"
                },
                "600": {
                    "value": "#7193A2",
                    "type": "color"
                },
                "700": {
                    "value": "#557482",
                    "type": "color"
                },
                "800": {
                    "value": "#3D535D",
                    "type": "color"
                },
                "900": {
                    "value": "#243238",
                    "type": "color"
                }
            },
            "international-blue": {
                "100": {
                    "value": "#D6E6E6",
                    "type": "color"
                },
                "200": {
                    "value": "#C1D9D9",
                    "type": "color"
                },
                "300": {
                    "value": "#ADCCCC",
                    "type": "color"
                },
                "400": {
                    "value": "#94BDBD",
                    "type": "color"
                },
                "500": {
                    "value": "#7BADAD",
                    "type": "color"
                },
                "600": {
                    "value": "#629393",
                    "type": "color"
                },
                "700": {
                    "value": "#4E7474",
                    "type": "color"
                },
                "800": {
                    "value": "#395656",
                    "type": "color"
                },
                "900": {
                    "value": "#253737",
                    "type": "color"
                }
            },
            "panorama-green": {
                "100": {
                    "value": "#E1E8E1",
                    "type": "color"
                },
                "200": {
                    "value": "#C7D4C7",
                    "type": "color"
                },
                "300": {
                    "value": "#AEC0AE",
                    "type": "color"
                },
                "400": {
                    "value": "#94AC94",
                    "type": "color"
                },
                "500": {
                    "value": "#7A987A",
                    "type": "color"
                },
                "600": {
                    "value": "#638163",
                    "type": "color"
                },
                "700": {
                    "value": "#4F674F",
                    "type": "color"
                },
                "800": {
                    "value": "#3B4D3B",
                    "type": "color"
                },
                "900": {
                    "value": "#273327",
                    "type": "color"
                }
            },
            "sport-green": {
                "100": {
                    "value": "#CCD4AF",
                    "type": "color"
                },
                "200": {
                    "value": "#BBC594",
                    "type": "color"
                },
                "300": {
                    "value": "#AAB779",
                    "type": "color"
                },
                "400": {
                    "value": "#99A95F",
                    "type": "color"
                },
                "500": {
                    "value": "#83914E",
                    "type": "color"
                },
                "600": {
                    "value": "#6E7A42",
                    "type": "color"
                },
                "700": {
                    "value": "#596335",
                    "type": "color"
                },
                "800": {
                    "value": "#444B29",
                    "type": "color"
                },
                "900": {
                    "value": "#2F341C",
                    "type": "color"
                }
            },
            "web-green": {
                "100": {
                    "value": "#D1DAC8",
                    "type": "color"
                },
                "200": {
                    "value": "#BDCAAF",
                    "type": "color"
                },
                "300": {
                    "value": "#A8BA97",
                    "type": "color"
                },
                "400": {
                    "value": "#94A97E",
                    "type": "color"
                },
                "500": {
                    "value": "#7F9966",
                    "type": "color"
                },
                "600": {
                    "value": "#6B8156",
                    "type": "color"
                },
                "700": {
                    "value": "#566845",
                    "type": "color"
                },
                "800": {
                    "value": "#425035",
                    "type": "color"
                },
                "900": {
                    "value": "#2E3725",
                    "type": "color"
                }
            },
            "epaper-purple": {
                "100": {
                    "value": "#C5C9D2",
                    "type": "color"
                },
                "200": {
                    "value": "#B1B6C2",
                    "type": "color"
                },
                "300": {
                    "value": "#9DA3B2",
                    "type": "color"
                },
                "400": {
                    "value": "#8990A2",
                    "type": "color"
                },
                "500": {
                    "value": "#757E93",
                    "type": "color"
                },
                "600": {
                    "value": "#626A7D",
                    "type": "color"
                },
                "700": {
                    "value": "#505666",
                    "type": "color"
                },
                "800": {
                    "value": "#3E434F",
                    "type": "color"
                },
                "900": {
                    "value": "#2C3038",
                    "type": "color"
                }
            },
            "klassik-blue": {
                "100": {
                    "value": "#E4ECEC",
                    "type": "color"
                },
                "200": {
                    "value": "#CCDBDB",
                    "type": "color"
                },
                "300": {
                    "value": "#B4CBCB",
                    "type": "color"
                },
                "400": {
                    "value": "#9CBABA",
                    "type": "color"
                },
                "500": {
                    "value": "#84A9A9",
                    "type": "color"
                },
                "600": {
                    "value": "#679394",
                    "type": "color"
                },
                "700": {
                    "value": "#527575",
                    "type": "color"
                },
                "800": {
                    "value": "#3D5757",
                    "type": "color"
                },
                "900": {
                    "value": "#283939",
                    "type": "color"
                }
            },
            "kompakt-orange": {
                "100": {
                    "value": "#E9DFD8",
                    "type": "color"
                },
                "200": {
                    "value": "#D7C5B7",
                    "type": "color"
                },
                "300": {
                    "value": "#C5AB96",
                    "type": "color"
                },
                "400": {
                    "value": "#B39075",
                    "type": "color"
                },
                "500": {
                    "value": "#9E7657",
                    "type": "color"
                },
                "600": {
                    "value": "#87654A",
                    "type": "color"
                },
                "700": {
                    "value": "#70543E",
                    "type": "color"
                },
                "800": {
                    "value": "#594231",
                    "type": "color"
                },
                "900": {
                    "value": "#423124",
                    "type": "color"
                }
            },
            "pur-blue": {
                "100": {
                    "value": "#E6EBEF",
                    "type": "color"
                },
                "200": {
                    "value": "#CCD8E0",
                    "type": "color"
                },
                "300": {
                    "value": "#B3C4D0",
                    "type": "color"
                },
                "400": {
                    "value": "#9AB1C1",
                    "type": "color"
                },
                "500": {
                    "value": "#819DB1",
                    "type": "color"
                },
                "600": {
                    "value": "#5F829B",
                    "type": "color"
                },
                "700": {
                    "value": "#4A6578",
                    "type": "color"
                },
                "800": {
                    "value": "#344755",
                    "type": "color"
                },
                "900": {
                    "value": "#1F2A33",
                    "type": "color"
                }
            },
            "purwochenende-green": {
                "100": {
                    "value": "#E8E8DE",
                    "type": "color"
                },
                "200": {
                    "value": "#D8D8C6",
                    "type": "color"
                },
                "300": {
                    "value": "#C7C7AD",
                    "type": "color"
                },
                "400": {
                    "value": "#B7B795",
                    "type": "color"
                },
                "500": {
                    "value": "#A6A67D",
                    "type": "color"
                },
                "600": {
                    "value": "#8F8F61",
                    "type": "color"
                },
                "700": {
                    "value": "#70704D",
                    "type": "color"
                },
                "800": {
                    "value": "#525238",
                    "type": "color"
                },
                "900": {
                    "value": "#343423",
                    "type": "color"
                }
            },
            "studentinnen-yellow": {
                "100": {
                    "value": "#E5E2D6",
                    "type": "color"
                },
                "200": {
                    "value": "#D4CEBA",
                    "type": "color"
                },
                "300": {
                    "value": "#C2BA9E",
                    "type": "color"
                },
                "400": {
                    "value": "#B0A681",
                    "type": "color"
                },
                "500": {
                    "value": "#9F9265",
                    "type": "color"
                },
                "600": {
                    "value": "#847952",
                    "type": "color"
                },
                "700": {
                    "value": "#675F41",
                    "type": "color"
                },
                "800": {
                    "value": "#4B452F",
                    "type": "color"
                },
                "900": {
                    "value": "#2F2B1D",
                    "type": "color"
                }
            },
            "supporter-yellow": {
                "50": {
                    "value": "#F1F0EB",
                    "type": "color"
                },
                "100": {
                    "value": "#EAE7E1",
                    "type": "color"
                },
                "200": {
                    "value": "#DBD7CC",
                    "type": "color"
                },
                "300": {
                    "value": "#CCC6B7",
                    "type": "color"
                },
                "400": {
                    "value": "#BDB6A2",
                    "type": "color"
                },
                "500": {
                    "value": "#AEA58E",
                    "type": "color"
                },
                "600": {
                    "value": "#978B6D",
                    "type": "color"
                },
                "700": {
                    "value": "#776D55",
                    "type": "color"
                },
                "800": {
                    "value": "#564F3D",
                    "type": "color"
                },
                "900": {
                    "value": "#363126",
                    "type": "color"
                }
            },
            "abo-sand": {
                "100": {
                    "value": "#ece8e4",
                    "type": "color"
                },
                "200": {
                    "value": "#d6cfc7",
                    "type": "color"
                },
                "300": {
                    "value": "#c1b6a9",
                    "type": "color"
                },
                "400": {
                    "value": "#ab9d8c",
                    "type": "color"
                },
                "500": {
                    "value": "#96846e",
                    "type": "color"
                },
                "600": {
                    "value": "#796a58",
                    "type": "color"
                },
                "700": {
                    "value": "#5c5042",
                    "type": "color"
                },
                "800": {
                    "value": "#3e362d",
                    "type": "color"
                },
                "900": {
                    "value": "#201c18",
                    "type": "color"
                }
            },
            "immo-green": {
                "50": {
                    "value": "#EDF2E7",
                    "type": "color"
                },
                "100": {
                    "value": "#E2EAD8",
                    "type": "color"
                },
                "200": {
                    "value": "#CCDABB",
                    "type": "color"
                },
                "300": {
                    "value": "#B6CA9D",
                    "type": "color"
                },
                "400": {
                    "value": "#9FBA7F",
                    "type": "color"
                },
                "500": {
                    "value": "#89AA61",
                    "type": "color"
                },
                "600": {
                    "value": "#72904D",
                    "type": "color"
                },
                "700": {
                    "value": "#5A723D",
                    "type": "color"
                },
                "800": {
                    "value": "#43542D",
                    "type": "color"
                },
                "900": {
                    "value": "#2B361D",
                    "type": "color"
                }
            },
            "jobs-blue": {
                "50": {
                    "value": "#F7FBFB",
                    "type": "color"
                },
                "100": {
                    "value": "#E6F1F3",
                    "type": "color"
                },
                "200": {
                    "value": "#C3DEE3",
                    "type": "color"
                },
                "300": {
                    "value": "#A0CAD3",
                    "type": "color"
                },
                "400": {
                    "value": "#7DB7C3",
                    "type": "color"
                },
                "500": {
                    "value": "#5AA4B3",
                    "type": "color"
                },
                "600": {
                    "value": "#488E9C",
                    "type": "color"
                },
                "700": {
                    "value": "#3B7580",
                    "type": "color"
                },
                "800": {
                    "value": "#2E5B64",
                    "type": "color"
                },
                "900": {
                    "value": "#214248",
                    "type": "color"
                }
            },
            "finden-red": {
                "50": {
                    "value": "#F7E4E5",
                    "type": "color"
                },
                "100": {
                    "value": "#F2D3D3",
                    "type": "color"
                },
                "200": {
                    "value": "#E8AFB0",
                    "type": "color"
                },
                "300": {
                    "value": "#DD8B8D",
                    "type": "color"
                },
                "400": {
                    "value": "#D3686A",
                    "type": "color"
                },
                "500": {
                    "value": "#C94447",
                    "type": "color"
                },
                "600": {
                    "value": "#AD3235",
                    "type": "color"
                },
                "700": {
                    "value": "#89282A",
                    "type": "color"
                },
                "800": {
                    "value": "#661E1F",
                    "type": "color"
                },
                "900": {
                    "value": "#421314",
                    "type": "color"
                }
            }
        }
    }
}